decoder_task24/decoder3x8.sv
module decoder3x8 (
    input  logic [2:0] in,      // 3-bit input
    output logic [7:0] out      // 8-bit output
);

    always_comb begin
        // Default all outputs to 0
        out = 8'b00000000;
        
        // Set the appropriate output bit based on the input
        case (in)
            3'b000: out = 8'b00000001;
            3'b001: out = 8'b00000010;
            3'b010: out = 8'b00000100;
            3'b011: out = 8'b00001000;
            3'b100: out = 8'b00010000;
            3'b101: out = 8'b00100000;
            3'b110: out = 8'b01000000;
            3'b111: out = 8'b10000000;
            default: out = 8'b00000000; // Default case, though not strictly necessary
        endcase
    end
endmodule

decoder_task24/tb/decoder3x8_tb.sv
module decoder3x8_tb;

  // Marking the start and end of Simulation
  initial $display("\033[7;36m TEST STARTED \033[0m");
  final   $display("\033[7;36m TEST ENDED \033[0m");


  //////////////////////////////////////////////////////////////////////////////
  //-SIGNALS
  //////////////////////////////////////////////////////////////////////////////

  logic         clk;  // simulation timing clock
  logic [2:0]   in;   // 3 bit input data

  logic [7:0]   out;  //out output data

  //////////////////////////////////////////////////////////////////////////////
  //-VARIABLES
  //////////////////////////////////////////////////////////////////////////////

  int         pass;  // number of time results did matched
  int         fail;  // number of time results did not matched

  //////////////////////////////////////////////////////////////////////////////
  //-RTL CONNECTON
  //////////////////////////////////////////////////////////////////////////////

  decoder3x8 dut01 (
      .in(in),
      .out(out)
  );

  //Driver Mailbox
  mailbox #(logic [2:0]) dvr_in_mbx    = new();
  
  //Monitor Mailbox For I/O
  mailbox #(logic [2:0]) moni_in_mbx   = new();
  mailbox #(logic [7:0]) moni_out_mbx  = new();




  //////////////////////////////////////////////////////////////////////////////
  //-METHODS
  //////////////////////////////////////////////////////////////////////////////

  // Apply system reset and initialize all inputs
  task static apply_reset();
    #100ns;
    clk  <= '0;
    in   <= '0;
    #100ns;
  endtask

  // start toggling system clock forever every 5ns
  task static start_clock();
    fork
      forever begin
        clk <= '1;
        #5ns;
        clk <= '0;
        #5ns;
      end
    join_none
  endtask

  task static driver_monitor_scoreboard();
    fork
        forever begin // in driver
            logic [2:0] data_in;
            dvr_in_mbx.get(data_in);
            in   <=  data_in;
            @(posedge clk);
        end

        forever begin // in monitor
            @ (posedge clk);
            moni_in_mbx.put(in);
            $display("input: %b",in);
        end

        forever begin // out monitor
            @ (posedge clk);
            moni_out_mbx.put(out);
            $display("Output: %b",out);
        end

    ////////////Scoreboard//////////////
 
        forever begin
            logic [7:0] expected_out;
            logic [2:0] A;
            logic [7:0] decoder_out;

            moni_in_mbx.get(A);
            moni_out_mbx.get(decoder_out);

            expected_out = 
                (A == 3'b000) ? 8'b00000001 : 
                (A == 3'b001) ? 8'b00000010 : 
                (A == 3'b010) ? 8'b00000100 : 
                (A == 3'b011) ? 8'b00001000 : 
                (A == 3'b100) ? 8'b00010000 : 
                (A == 3'b101) ? 8'b00100000 : 
                (A == 3'b110) ? 8'b01000000 : 
                (A == 3'b111) ? 8'b10000000 : 8'b00000000; 

            if(expected_out === decoder_out) pass++;
            else fail++;
        end
    join_none
  endtask

    ///////////////End Scoreboard////////////////

  //////////////////////////////////////////////////////////////////////////////
  //-PROCEDURALS
  //////////////////////////////////////////////////////////////////////////////

  initial begin  // main initial
    $dumpfile("dump.vcd");
    $dumpvars;

    apply_reset();
    start_clock();

    driver_monitor_scoreboard();

    // letting things run for 10 posedge of clk
    @(posedge clk); 
    repeat(10) begin
        dvr_in_mbx.put($urandom);
    end

    repeat(15) @(posedge clk);
    //driver_monitor_scoreboard();

    // printing out number of passes out of total
    $display("\033[1;33m%0d/%0d PASSED\033[0m", pass, pass + fail);

    // end simulation
    $finish;

  end

endmodule

decoder_task24/dump.vcd
$date
   Fri Jun 21 18:38:03 2024
$end

$version
  2024.1
  $dumpfile ("dump.vcd") 
$end

$timescale
  1ps
$end

$scope module decoder3x8_tb $end
$var reg 1 ! clk $end
$var reg 3 " in [2:0] $end
$var reg 8 # out [7:0] $end
$var reg 32 $ pass [31:0] $end
$var reg 32 % fail [31:0] $end
$var reg 32 & dvr_in_mbx $end
$var reg 32 ' moni_in_mbx $end
$var reg 32 ( moni_out_mbx $end
$scope module dut01 $end
$var wire 3 ) in [2:0] $end
$var reg 8 # out [7:0] $end
$upscope $end
$scope task apply_reset $end
$upscope $end
$scope task start_clock $end
$upscope $end
$scope task driver_monitor_scoreboard $end
$scope begin Block69_5 $end
$var reg 3 * data_in [2:0] $end
$upscope $end
$scope begin Block90_9 $end
$var reg 8 + expected_out [7:0] $end
$var reg 3 , A [2:0] $end
$var reg 8 - decoder_out [7:0] $end
$upscope $end
$upscope $end
$upscope $end
$enddefinitions $end

#0
$dumpvars
x!
bx "
b0 #
b0 $
b0 %
b100001101110010000000000111000 &
b100001101110010000000010101000 '
b100001101110010000000100011000 (
bx )
bx *
bx +
bx ,
bx -
$end

#100000
0!
b0 "
b1 #
b0 )

#200000
1!
b1 $
b0 *
b1 +
b0 ,
b1 -

#205000
0!

#210000
1!
b100 "
b10000 #
b10 $
b100 )
b100 *

#215000
0!

#220000
1!
b11 $
b10000 +
b100 ,
b10000 -

#225000
0!

#230000
1!
b110 "
b1000000 #
b100 $
b110 )
b110 *

#235000
0!

#240000
1!
b101 "
b100000 #
b101 $
b101 )
b101 *
b1000000 +
b110 ,
b1000000 -

#245000
0!

#250000
1!
b0 "
b1 #
b110 $
b0 )
b0 *
b100000 +
b101 ,
b100000 -

#255000
0!

#260000
1!
b111 "
b10000000 #
b111 $
b111 )
b111 *
b1 +
b0 ,
b1 -

#265000
0!

#270000
1!
b110 "
b1000000 #
b1000 $
b110 )
b110 *
b10000000 +
b111 ,
b10000000 -

#275000
0!

#280000
1!
b100 "
b10000 #
b1001 $
b100 )
b100 *
b1000000 +
b110 ,
b1000000 -

#285000
0!

#290000
1!
b1010 $
b10000 +
b100 ,
b10000 -

#295000
0!

#300000
1!
b1011 $

#305000
0!

#310000
1!
b1100 $

#315000
0!

#320000
1!
b1101 $

#325000
0!

#330000
1!
b1110 $

#335000
0!

#340000
1!
b1111 $

