task25/moore_o_1010.sv
////////////1010 Overlapping Moore Sequence Detector////////////
module moore_o_1010(
        input logic in,
        input logic clk, 
        input logic rst_n, 
        output logic out
);
        ////////////Parameter////////////
        parameter S0 = 3'b001;
        parameter S1 = 3'b010;
        parameter S2 = 3'b011;
        parameter S3 = 3'b100;
        parameter S4 = 3'b101; // extra state when compared with Mealy Machine
        ////////////State////////////  
        logic [3:0] p_state, n_state;
        ////////////Clock and Reset////////////
        always @(posedge clk or negedge rst_n) begin
        if(!rst_n) begin 
            p_state <= S0;
        end
        else 
            p_state <= n_state;
        end
        ////////////Input Case////////////  
        always @(p_state or in) begin
         case(p_state)
            S0: begin
            if(in == 0) n_state = S0;
            else        n_state = S1;
            end
            S1: begin
            if(in == 0) n_state = S2;
            else        n_state = S1;
            end
            S2: begin
            if(in == 0) n_state = S0;
            else        n_state = S3;
            end
            S3: begin
            if(in == 0) n_state = S4;
            else        n_state = S1;
            end
            S4: begin
            if(in == 0) n_state = S0;
            else        n_state = S3;
            end
            default:    n_state = S0;
        endcase
        end
        ////////////Output Case////////////        
        always@(p_state) begin
         case(p_state)
            S0 :      out = 0;
            S1 :      out = 0;
            S2 :      out = 0;
            S3 :      out = 0;
            S4 :      out = 1;
            default : out = 0;
        endcase
        end
endmodule

task25/moore_o_1010_tb.sv
module moore_o_1010_tb;

    // Marking the start and end of Simulation
    initial $display("\033[7;36m TEST STARTED \033[0m");
    final   $display("\033[7;36m TEST ENDED \033[0m");

    //////////////////////////////////////////////////////////////////////////////
    //-SIGNALS
    //////////////////////////////////////////////////////////////////////////////

    logic   in;     // simulation timing clock
    logic   clk;    // simulation timing clock
    logic   rst_n;  // simulation timing clock
    logic   out;    //out output data

    //////////////////////////////////////////////////////////////////////////////
    //-VARIABLES
    //////////////////////////////////////////////////////////////////////////////

    int         pass;  // number of time results did matched
    int         fail;  // number of time results did not matched

    //////////////////////////////////////////////////////////////////////////////
    //-RTL CONNECTON
    //////////////////////////////////////////////////////////////////////////////

    moore_o_1010 u_moore (
        .in(in),
        .clk(clk),
        .rst_n(rst_n),
        .out(out)
    );

    //Driver Mailbox
    mailbox #(logic) dvr_mbx        = new();

    //Monitor Mailbox For I/O
    mailbox #(logic) mon_in_mbx     = new();
    mailbox #(logic) mon_out_mbx    = new();


    //////////////////////////////////////////////////////////////////////////////
    //-METHODS
    //////////////////////////////////////////////////////////////////////////////

    // Apply system reset and initialize all inputs
    task static apply_reset();
        #10ns;
        clk     <= '0;
        rst_n   <= '0;
        in      <= '0;
        #10ns;
        rst_n   <= '1;
    endtask

    // start toggling system clock forever every 5ns
    task static start_clock();
        fork
            forever begin
                clk <= '1;
                #5ns;
                clk <= '0;
                #5ns;
        end
        join_none
    endtask

    task static driver_monitor_scoreboard();
        fork
            forever begin // in driver
                logic x;
                dvr_mbx.get(x);
                in <= x;
                @(posedge clk);
            end

            forever begin // in monitor
                @ (posedge clk);
                mon_in_mbx.put(in);
            end

            forever begin // out monitor
                @ (posedge clk);
                mon_out_mbx.put(out);
            end

            //////////////////////////////////////
            //////////// Scoreboard //////////////
            //////////////////////////////////////

            forever begin
                logic inputs;
                logic [3:0] in_seq;
                logic moore_out;

                mon_in_mbx.get(inputs);
                mon_out_mbx.get(moore_out);

           /////////// input sequence ////////////

                /*in_seq[0] <= inputs;
                in_seq[1] <= in_seq[0];
                in_seq[2] <= in_seq[1];
                in_seq[3] <= in_seq[2]; */
                in_seq <= {in_seq[2:0],inputs};

                $display("inputs sequence: %b",in_seq);
                $display("Output: %b",out);
                $display("input: %b",inputs);
 
                if(in_seq === 4'b1010) moore_out =1;
                else moore_out =0;

                if (moore_out === out)
                        pass++;
                else fail++;
            end
        join_none
    endtask
    /////////////////////////////////////////////
    ///////////////End Scoreboard////////////////
    /////////////////////////////////////////////


  //////////////////////////////////////////////////////////////////////////////
  //-PROCEDURALS
  //////////////////////////////////////////////////////////////////////////////

  initial begin  // main initial
    $dumpfile("dump.vcd");
    $dumpvars;

    apply_reset();
    start_clock();

    driver_monitor_scoreboard();

    // letting things run for 10 posedge of clk
    @(posedge clk);
    repeat(100) begin
        dvr_mbx.put($urandom);
    end

    repeat(110) @(posedge clk);
    //driver_monitor_scoreboard();

    // printing out number of passes out of total
    $display("\033[1;33m%0d/%0d PASSED\033[0m", pass, pass + fail);

    // end simulation
    $finish;

  end

endmodule

task25/dump.vcd
$date
   Tue Jun 25 11:02:11 2024
$end

$version
  2024.1
  $dumpfile ("dump.vcd") 
$end

$timescale
  1ps
$end

$scope module moore_o_1010_tb $end
$var reg 1 ! in $end
$var reg 1 " clk $end
$var reg 1 # rst_n $end
$var reg 1 $ out $end
$var reg 32 % pass [31:0] $end
$var reg 32 & fail [31:0] $end
$var reg 32 ' dvr_mbx $end
$var reg 32 ( mon_in_mbx $end
$var reg 32 ) mon_out_mbx $end
$scope module u_moore $end
$var wire 1 * in $end
$var wire 1 + clk $end
$var wire 1 , rst_n $end
$var reg 1 $ out $end
$var reg 4 - p_state [3:0] $end
$var reg 4 . n_state [3:0] $end
$upscope $end
$scope task apply_reset $end
$upscope $end
$scope task start_clock $end
$upscope $end
$scope task driver_monitor_scoreboard $end
$scope begin Block70_7 $end
$var reg 1 / x $end
$upscope $end
$scope begin Block91_11 $end
$var reg 1 0 inputs $end
$var reg 4 1 in_seq [3:0] $end
$var reg 1 2 moore_out $end
$upscope $end
$upscope $end
$upscope $end
$enddefinitions $end

#0
$dumpvars
x!
x"
x#
x$
b0 %
b0 &
b100001101110100000000000111000 '
b100001101110100000000010101000 (
b100001101110100000000100011000 )
x*
x+
x,
bx -
bx .
x/
x0
bx 1
x2
$end

#10000
0!
0"
0#
0$
0*
0+
0,
b1 -
b1 .

#20000
1"
1#
b1 %
1+
1,
0/
00
bx0 1
02

#25000
0"
0+

#30000
1!
1"
b10 %
1*
1+
b10 .
1/
bx00 1

#35000
0"
0+

#40000
0!
1"
b11 %
0*
1+
b10 -
b11 .
0/
10
bx001 1

#45000
0"
0+

#50000
1"
b100 %
1+
b11 -
b1 .
00
b10 1

#55000
0"
0+

#60000
1!
1"
b101 %
1*
1+
b1 -
b10 .
1/
b100 1

#65000
0"
0+

#70000
0!
1"
b110 %
0*
1+
b10 -
b11 .
0/
10
b1001 1

#75000
0"
0+

#80000
1!
1"
b111 %
1*
1+
b11 -
b100 .
1/
00
b10 1

#85000
0"
0+

#90000
1"
b1000 %
1+
b100 -
b10 .
10
b101 1

#95000
0"
0+

#100000
1"
b1001 %
1+
b10 -
b1011 1

#105000
0"
0+

#110000
1"
b1010 %
1+
b111 1

#115000
0"
0+

#120000
1"
b1011 %
1+
b1111 1

#125000
0"
0+

#130000
0!
1"
b1100 %
0*
1+
b11 .
0/

#135000
0"
0+

#140000
1!
1"
b1101 %
1*
1+
b11 -
b100 .
1/
00
b1110 1

#145000
0"
0+

#150000
0!
1"
b1110 %
0*
1+
b100 -
b101 .
0/
10
b1101 1

#155000
0"
0+

#160000
1!
1"
1$
b1111 %
1*
1+
b101 -
b100 .
1/
00
b1010 1

#165000
0"
0+

#170000
0!
1"
0$
b10000 %
0*
1+
b100 -
b101 .
0/
10
b101 1
12

#175000
0"
0+

#180000
1"
1$
b10001 %
1+
b101 -
b1 .
00
b1010 1
02

#185000
0"
0+

#190000
1!
1"
0$
b10010 %
1*
1+
b1 -
b10 .
1/
b100 1
12

#195000
0"
0+

#200000
0!
1"
b10011 %
0*
1+
b10 -
b11 .
0/
10
b1001 1
02

#205000
0"
0+

#210000
1!
1"
b10100 %
1*
1+
b11 -
b100 .
1/
00
b10 1

#215000
0"
0+

#220000
1"
b10101 %
1+
b100 -
b10 .
10
b101 1

#225000
0"
0+

#230000
0!
1"
b10110 %
0*
1+
b10 -
b11 .
0/
b1011 1

#235000
0"
0+

#240000
1"
b10111 %
1+
b11 -
b1 .
00
b110 1

#245000
0"
0+

#250000
1!
1"
b11000 %
1*
1+
b1 -
b10 .
1/
b1100 1

#255000
0"
0+

#260000
1"
b11001 %
1+
b10 -
10
b1001 1

#265000
0"
0+

#270000
0!
1"
b11010 %
0*
1+
b11 .
0/
b11 1

#275000
0"
0+

#280000
1!
1"
b11011 %
1*
1+
b11 -
b100 .
1/
00
b110 1

#285000
0"
0+

#290000
0!
1"
b11100 %
0*
1+
b100 -
b101 .
0/
10
b1101 1

#295000
0"
0+

#300000
1"
1$
b11101 %
1+
b101 -
b1 .
00
b1010 1

#305000
0"
0+

#310000
1!
1"
0$
b11110 %
1*
1+
b1 -
b10 .
1/
b100 1
12

#315000
0"
0+

#320000
0!
1"
b11111 %
0*
1+
b10 -
b11 .
0/
10
b1001 1
02

#325000
0"
0+

#330000
1!
1"
b100000 %
1*
1+
b11 -
b100 .
1/
00
b10 1

#335000
0"
0+

#340000
1"
b100001 %
1+
b100 -
b10 .
10
b101 1

#345000
0"
0+

#350000
1"
b100010 %
1+
b10 -
b1011 1

#355000
0"
0+

#360000
0!
1"
b100011 %
0*
1+
b11 .
0/
b111 1

#365000
0"
0+

#370000
1"
b100100 %
1+
b11 -
b1 .
00
b1110 1

#375000
0"
0+

#380000
1"
b100101 %
1+
b1 -
b1100 1

#385000
0"
0+

#390000
1"
b100110 %
1+
b1000 1

#395000
0"
0+

#400000
1!
1"
b100111 %
1*
1+
b10 .
1/
b0 1

#405000
0"
0+

#410000
1"
b101000 %
1+
b10 -
10
b1 1

#415000
0"
0+

#420000
1"
b101001 %
1+
b11 1

#425000
0"
0+

#430000
1"
b101010 %
1+
b111 1

#435000
0"
0+

#440000
1"
b101011 %
1+
b1111 1

#445000
0"
0+

#450000
1"
b101100 %
1+

#455000
0"
0+

#460000
1"
b101101 %
1+

#465000
0"
0+

#470000
1"
b101110 %
1+

#475000
0"
0+

#480000
0!
1"
b101111 %
0*
1+
b11 .
0/

#485000
0"
0+

#490000
1"
b110000 %
1+
b11 -
b1 .
00
b1110 1

#495000
0"
0+

#500000
1"
b110001 %
1+
b1 -
b1100 1

#505000
0"
0+

#510000
1"
b110010 %
1+
b1000 1

#515000
0"
0+

#520000
1!
1"
b110011 %
1*
1+
b10 .
1/
b0 1

#525000
0"
0+

#530000
0!
1"
b110100 %
0*
1+
b10 -
b11 .
0/
10
b1 1

#535000
0"
0+

#540000
1!
1"
b110101 %
1*
1+
b11 -
b100 .
1/
00
b10 1

#545000
0"
0+

#550000
0!
1"
b110110 %
0*
1+
b100 -
b101 .
0/
10
b101 1

#555000
0"
0+

#560000
1"
1$
b110111 %
1+
b101 -
b1 .
00
b1010 1

#565000
0"
0+

#570000
1!
1"
0$
b111000 %
1*
1+
b1 -
b10 .
1/
b100 1
12

#575000
0"
0+

#580000
0!
1"
b111001 %
0*
1+
b10 -
b11 .
0/
10
b1001 1
02

#585000
0"
0+

#590000
1"
b111010 %
1+
b11 -
b1 .
00
b10 1

#595000
0"
0+

#600000
1!
1"
b111011 %
1*
1+
b1 -
b10 .
1/
b100 1

#605000
0"
0+

#610000
1"
b111100 %
1+
b10 -
10
b1001 1

#615000
0"
0+

#620000
0!
1"
b111101 %
0*
1+
b11 .
0/
b11 1

#625000
0"
0+

#630000
1"
b111110 %
1+
b11 -
b1 .
00
b110 1

#635000
0"
0+

#640000
1"
b111111 %
1+
b1 -
b1100 1

#645000
0"
0+

#650000
1"
b1000000 %
1+
b1000 1

#655000
0"
0+

#660000
1"
b1000001 %
1+
b0 1

#665000
0"
0+

#670000
1"
b1000010 %
1+

#675000
0"
0+

#680000
1!
1"
b1000011 %
1*
1+
b10 .
1/

#685000
0"
0+

#690000
0!
1"
b1000100 %
0*
1+
b10 -
b11 .
0/
10
b1 1

#695000
0"
0+

#700000
1"
b1000101 %
1+
b11 -
b1 .
00
b10 1

#705000
0"
0+

#710000
1!
1"
b1000110 %
1*
1+
b1 -
b10 .
1/
b100 1

#715000
0"
0+

#720000
0!
1"
b1000111 %
0*
1+
b10 -
b11 .
0/
10
b1001 1

#725000
0"
0+

#730000
1"
b1001000 %
1+
b11 -
b1 .
00
b10 1

#735000
0"
0+

#740000
1!
1"
b1001001 %
1*
1+
b1 -
b10 .
1/
b100 1

#745000
0"
0+

#750000
1"
b1001010 %
1+
b10 -
10
b1001 1

#755000
0"
0+

#760000
0!
1"
b1001011 %
0*
1+
b11 .
0/
b11 1

#765000
0"
0+

#770000
1!
1"
b1001100 %
1*
1+
b11 -
b100 .
1/
00
b110 1

#775000
0"
0+

#780000
0!
1"
b1001101 %
0*
1+
b100 -
b101 .
0/
10
b1101 1

#785000
0"
0+

#790000
1"
1$
b1001110 %
1+
b101 -
b1 .
00
b1010 1

#795000
0"
0+

#800000
1!
1"
0$
b1001111 %
1*
1+
b1 -
b10 .
1/
b100 1
12

#805000
0"
0+

#810000
0!
1"
b1010000 %
0*
1+
b10 -
b11 .
0/
10
b1001 1
02

#815000
0"
0+

#820000
1!
1"
b1010001 %
1*
1+
b11 -
b100 .
1/
00
b10 1

#825000
0"
0+

#830000
1"
b1010010 %
1+
b100 -
b10 .
10
b101 1

#835000
0"
0+

#840000
1"
b1010011 %
1+
b10 -
b1011 1

#845000
0"
0+

#850000
1"
b1010100 %
1+
b111 1

#855000
0"
0+

#860000
1"
b1010101 %
1+
b1111 1

#865000
0"
0+

#870000
1"
b1010110 %
1+

#875000
0"
0+

#880000
1"
b1010111 %
1+

#885000
0"
0+

#890000
0!
1"
b1011000 %
0*
1+
b11 .
0/

#895000
0"
0+

#900000
1"
b1011001 %
1+
b11 -
b1 .
00
b1110 1

#905000
0"
0+

#910000
1!
1"
b1011010 %
1*
1+
b1 -
b10 .
1/
b1100 1

#915000
0"
0+

#920000
0!
1"
b1011011 %
0*
1+
b10 -
b11 .
0/
10
b1001 1

#925000
0"
0+

#930000
1"
b1011100 %
1+
b11 -
b1 .
00
b10 1

#935000
0"
0+

#940000
1"
b1011101 %
1+
b1 -
b100 1

#945000
0"
0+

#950000
1!
1"
b1011110 %
1*
1+
b10 .
1/
b1000 1

#955000
0"
0+

#960000
0!
1"
b1011111 %
0*
1+
b10 -
b11 .
0/
10
b1 1

#965000
0"
0+

#970000
1"
b1100000 %
1+
b11 -
b1 .
00
b10 1

#975000
0"
0+

#980000
1"
b1100001 %
1+
b1 -
b100 1

#985000
0"
0+

#990000
1"
b1100010 %
1+
b1000 1

#995000
0"
0+

#1000000
1"
b1100011 %
1+
b0 1

#1005000
0"
0+

#1010000
1"
b1100100 %
1+

#1015000
0"
0+

#1020000
1"
b1100101 %
1+

#1025000
0"
0+

#1030000
1"
b1100110 %
1+

#1035000
0"
0+

#1040000
1"
b1100111 %
1+

#1045000
0"
0+

#1050000
1"
b1101000 %
1+

#1055000
0"
0+

#1060000
1"
b1101001 %
1+

#1065000
0"
0+

#1070000
1"
b1101010 %
1+

#1075000
0"
0+

#1080000
1"
b1101011 %
1+

#1085000
0"
0+

#1090000
1"
b1101100 %
1+

#1095000
0"
0+

#1100000
1"
b1101101 %
1+

#1105000
0"
0+

#1110000
1"
b1101110 %
1+

